schalter/__init__.py
schalter/config_scope.py
schalter/schalter.py
schalter-0.3a0.dist-info/LICENSE
schalter-0.3a0.dist-info/METADATA
schalter-0.3a0.dist-info/WHEEL
schalter-0.3a0.dist-info/top_level.txt
schalter-0.3a0.dist-info/RECORD
