Metadata-Version: 2.1
Name: schalter
Version: 0.3a0
Summary: Fast and simple configuration
Home-page: http://github.com/risteon/schalter
Author: Christoph Rist
Author-email: c.rist@posteo.de
License: Apache-2.0
Platform: UNKNOWN
Classifier: Development Status :: 3 - Alpha
Classifier: Intended Audience :: Developers
Requires-Python: >=3.6
Requires-Dist: decorator
Requires-Dist: ruamel.yaml
Provides-Extra: test
Requires-Dist: pytest ; extra == 'test'
Requires-Dist: pytest-cov ; extra == 'test'
